{"assets":{"0140AD956977053E067D61A2F3E68396":{"type":"texture","index":69,"assetRequest":{"type":"slide","state":"contents","slide":"9D8FD148-CA2F-4590-AA32-426EAFDA0DFF"},"url":{"web":"assets/0140AD956977053E067D61A2F3E68396.svg"},"width":336,"height":42},"FD5C3ED2E7434E6BDFE9C06C3ED1715E":{"type":"texture","index":73,"assetRequest":{"type":"slide","state":"contents","slide":"9D8FD148-CA2F-4590-AA32-426EAFDA0DFF"},"url":{"web":"assets/FD5C3ED2E7434E6BDFE9C06C3ED1715E.svg"},"width":785,"height":547},"C25C25FF361FB24FC35F6B120D2F252D":{"type":"texture","index":67,"assetRequest":{"type":"slide","state":"contents","slide":"9D8FD148-CA2F-4590-AA32-426EAFDA0DFF"},"url":{"web":"assets/C25C25FF361FB24FC35F6B120D2F252D.svg"},"width":1920,"height":1080},"015F7C12121A4F77FD7EC7C29E1BAA80":{"type":"texture","index":71,"assetRequest":{"type":"slide","state":"contents","slide":"9D8FD148-CA2F-4590-AA32-426EAFDA0DFF"},"url":{"web":"assets/015F7C12121A4F77FD7EC7C29E1BAA80.svg"},"width":1187,"height":377},"DBA6C240F4FFF39844A44556BE2C2CF7":{"type":"texture","index":70,"assetRequest":{"type":"slide","state":"contents","slide":"9D8FD148-CA2F-4590-AA32-426EAFDA0DFF"},"url":{"web":"assets/DBA6C240F4FFF39844A44556BE2C2CF7.svg"},"width":758,"height":47},"B20313EA5DF59806F414B64E69A6A7E8":{"type":"texture","index":75,"assetRequest":{"type":"slide","state":"incoming","slide":"9C68795E-CB40-4219-A3C6-9E8CF45F533E"},"url":{"web":"assets/B20313EA5DF59806F414B64E69A6A7E8.svg"},"width":1920,"height":1080},"CDC5FF49500FCCB406DE3F065BDECC81":{"type":"texture","index":68,"assetRequest":{"type":"slide","state":"contents","slide":"9D8FD148-CA2F-4590-AA32-426EAFDA0DFF"},"url":{"web":"assets/CDC5FF49500FCCB406DE3F065BDECC81.svg"},"width":542,"height":85},"16CEFB3D535DEAF8E33B75781567E5AB":{"type":"texture","index":74,"assetRequest":{"type":"slide","state":"outgoing","slide":"9D8FD148-CA2F-4590-AA32-426EAFDA0DFF"},"url":{"web":"assets/16CEFB3D535DEAF8E33B75781567E5AB.svg"},"width":1920,"height":1080},"1785A4D437AB25764E6B3795F35A733C":{"type":"texture","index":72,"assetRequest":{"type":"slide","state":"contents","slide":"9D8FD148-CA2F-4590-AA32-426EAFDA0DFF"},"url":{"web":"assets/1785A4D437AB25764E6B3795F35A733C.svg"},"width":1055,"height":48}},"events":[{"effects":[{"beginTime":0,"baseLayer":{"animations":[],"initialState":{"affineTransform":[1,0,0,1,0,0],"masksToBounds":false,"rotation":0,"scale":1,"position":{"pointX":960,"pointY":617.5},"width":1654,"sublayerTransform":[1,0,0,0,0,1,0,0,0,0,1,0,0,0,0,1],"contentsRect":{"y":0,"x":0,"width":1,"height":1},"opacity":1,"edgeAntialiasingMask":251658240,"height":725,"hidden":false,"anchorPoint":{"pointX":0.5,"pointY":0.5}},"objectID":"FB6CB0C2-F793-4CCB-AE07-F86A6CECF5A9","layers":[{"animations":[],"initialState":{"affineTransform":[1,0,0,1,0,0],"masksToBounds":false,"rotation":0,"scale":1,"position":{"pointX":827,"pointY":285},"width":1654,"sublayerTransform":[1,0,0,0,0,1,0,0,0,0,1,-0.0003500791246677598,0,0,0,1],"contentsRect":{"y":0,"x":0,"width":1,"height":1},"opacity":1,"edgeAntialiasingMask":251658240,"height":725,"hidden":false,"anchorPoint":{"pointX":0.5,"pointY":0.3931034482758621}},"layers":[{"animations":[{"timeOffset":0,"beginTime":1e-100,"repeatCount":0,"animations":[{"timeOffset":0,"from":{"scalar":0},"beginTime":0,"repeatCount":0,"fillMode":"both","duration":1,"autoreverses":false,"timingFunction":"EaseInEaseOut","property":"opacity","to":{"scalar":1}},{"timeOffset":0,"from":{"scalar":false},"beginTime":0,"repeatCount":0,"fillMode":"forwards","property":"hidden","autoreverses":false,"duration":1,"to":{"scalar":false}}],"fillMode":"both","autoreverses":false,"duration":1}],"layers":[],"initialState":{"affineTransform":[1,0,0,1,0,0],"masksToBounds":false,"rotation":0,"scale":1,"position":{"pointX":172,"pointY":35},"width":336,"sublayerTransform":[1,0,0,0,0,1,0,0,0,0,1,0,0,0,0,1],"contentsRect":{"y":0,"x":0,"width":1,"height":1},"opacity":1,"edgeAntialiasingMask":0,"height":42,"hidden":true,"anchorPoint":{"pointX":0.5,"pointY":0.5}},"texture":"0140AD956977053E067D61A2F3E68396"}]},{"animations":[],"layers":[],"initialState":{"affineTransform":[1,0,0,1,0,0],"masksToBounds":false,"rotation":0,"scale":1,"position":{"pointX":383,"pointY":147.5},"width":758,"sublayerTransform":[1,0,0,0,0,1,0,0,0,0,1,0,0,0,0,1],"contentsRect":{"y":0,"x":0,"width":1,"height":1},"opacity":1,"edgeAntialiasingMask":0,"height":47,"hidden":true,"anchorPoint":{"pointX":0.5,"pointY":0.5}},"texture":"DBA6C240F4FFF39844A44556BE2C2CF7"},{"animations":[],"layers":[],"initialState":{"affineTransform":[1,0,0,1,0,0],"masksToBounds":false,"rotation":0,"scale":1,"position":{"pointX":597.5,"pointY":421.5},"width":1187,"sublayerTransform":[1,0,0,0,0,1,0,0,0,0,1,0,0,0,0,1],"contentsRect":{"y":0,"x":0,"width":1,"height":1},"opacity":1,"edgeAntialiasingMask":0,"height":377,"hidden":true,"anchorPoint":{"pointX":0.5,"pointY":0.5}},"texture":"015F7C12121A4F77FD7EC7C29E1BAA80"},{"animations":[],"layers":[],"initialState":{"affineTransform":[1,0,0,1,0,0],"masksToBounds":false,"rotation":0,"scale":1,"position":{"pointX":531.5,"pointY":696},"width":1055,"sublayerTransform":[1,0,0,0,0,1,0,0,0,0,1,0,0,0,0,1],"contentsRect":{"y":0,"x":0,"width":1,"height":1},"opacity":1,"edgeAntialiasingMask":0,"height":48,"hidden":true,"anchorPoint":{"pointX":0.5,"pointY":0.5}},"texture":"1785A4D437AB25764E6B3795F35A733C"}]},"effects":[{"beginTime":0,"baseLayer":{"animations":[],"initialState":{"affineTransform":[1,0,0,1,0,0],"masksToBounds":false,"rotation":0,"scale":1,"position":{"pointX":1474.616554054055,"pointY":413.9885979729729},"width":772,"sublayerTransform":[1,0,0,0,0,1,0,0,0,0,1,0,0,0,0,1],"contentsRect":{"y":0,"x":0,"width":1,"height":1},"opacity":1,"edgeAntialiasingMask":251658240,"height":301.9999999999999,"hidden":false,"anchorPoint":{"pointX":0.5,"pointY":0.5}},"objectID":"FE480AE0-80EB-4DDA-9725-1C2655EEFDB7","layers":[{"animations":[],"initialState":{"affineTransform":[1,0,0,1,0,0],"masksToBounds":false,"rotation":0,"scale":1,"position":{"pointX":-128.6165540540551,"pointY":277.0114020270271},"width":772,"sublayerTransform":[1,0,0,0,0,1,0,0,0,0,1,-0.0003500791246677598,0,0,0,1],"contentsRect":{"y":0,"x":0,"width":1,"height":1},"opacity":1,"edgeAntialiasingMask":251658240,"height":301.9999999999999,"hidden":false,"anchorPoint":{"pointX":-0.1666017539560299,"pointY":0.9172562981027389}},"layers":[{"animations":[{"timeOffset":0,"beginTime":1e-100,"repeatCount":0,"animations":[{"timeOffset":0,"from":{"scalar":0},"beginTime":0,"repeatCount":0,"fillMode":"both","duration":1,"autoreverses":false,"timingFunction":"EaseInEaseOut","property":"opacity","to":{"scalar":1}},{"timeOffset":0,"from":{"scalar":false},"beginTime":0,"repeatCount":0,"fillMode":"forwards","property":"hidden","autoreverses":false,"duration":1,"to":{"scalar":false}}],"fillMode":"both","autoreverses":false,"duration":1}],"layers":[],"initialState":{"affineTransform":[1,0,0,1,0,0],"masksToBounds":false,"rotation":0,"scale":1,"position":{"pointX":385.8834459459449,"pointY":150.511402027027},"width":785,"sublayerTransform":[1,0,0,0,0,1,0,0,0,0,1,0,0,0,0,1],"contentsRect":{"y":0,"x":0,"width":1,"height":1},"opacity":1,"edgeAntialiasingMask":0,"height":547,"hidden":true,"anchorPoint":{"pointX":0.5,"pointY":0.5}},"texture":"FD5C3ED2E7434E6BDFE9C06C3ED1715E"}]}]},"effects":[],"duration":1,"type":"buildIn","name":"apple:dissolve","objectID":"FE480AE0-80EB-4DDA-9725-1C2655EEFDB7"}],"duration":1,"type":"buildIn","name":"apple:dissolve character","objectID":"FB6CB0C2-F793-4CCB-AE07-F86A6CECF5A9"}],"automaticPlay":false,"hyperlinks":[],"accessibility":[{"text":"Decorators","targetRectangle":{"y":98,"x":683.024,"width":553.9520000000001,"height":134}}],"baseLayer":{"animations":[],"initialState":{"affineTransform":[1,0,0,1,0,0],"masksToBounds":false,"rotation":0,"scale":1,"position":{"pointX":960,"pointY":540},"width":1920,"sublayerTransform":[1,0,0,0,0,1,0,0,0,0,1,0,0,0,0,1],"contentsRect":{"y":0,"x":0,"width":1,"height":1},"opacity":1,"edgeAntialiasingMask":251658240,"height":1080,"hidden":false,"anchorPoint":{"pointX":0.5,"pointY":0.5}},"layers":[{"animations":[],"initialState":{"affineTransform":[1,0,0,1,0,0],"masksToBounds":false,"rotation":0,"scale":1,"position":{"pointX":960,"pointY":540},"width":1920,"sublayerTransform":[1,0,0,0,0,1,0,0,0,0,1,0,0,0,0,1],"contentsRect":{"y":0,"x":0,"width":1,"height":1},"opacity":1,"edgeAntialiasingMask":251658240,"height":1080,"hidden":false,"anchorPoint":{"pointX":0.5,"pointY":0.5}},"layers":[{"animations":[],"initialState":{"affineTransform":[1,0,0,1,0,0],"masksToBounds":false,"rotation":0,"scale":1,"position":{"pointX":960,"pointY":540},"width":1920,"sublayerTransform":[1,0,0,0,0,1,0,0,0,0,1,0,0,0,0,1],"contentsRect":{"y":0,"x":0,"width":1,"height":1},"opacity":1,"edgeAntialiasingMask":251658240,"height":1080,"hidden":false,"anchorPoint":{"pointX":0.5,"pointY":0.5}},"layers":[{"animations":[],"layers":[],"initialState":{"affineTransform":[1,0,0,1,0,0],"masksToBounds":false,"rotation":0,"scale":1,"position":{"pointX":960,"pointY":540},"width":1920,"sublayerTransform":[1,0,0,0,0,1,0,0,0,0,1,0,0,0,0,1],"contentsRect":{"y":0,"x":0,"width":1,"height":1},"opacity":1,"edgeAntialiasingMask":0,"height":1080,"hidden":false,"anchorPoint":{"pointX":0.5,"pointY":0.5}},"texture":"C25C25FF361FB24FC35F6B120D2F252D"}]}]},{"animations":[],"initialState":{"affineTransform":[1,0,0,1,0,0],"masksToBounds":false,"rotation":0,"scale":1,"position":{"pointX":960,"pointY":540},"width":1920,"sublayerTransform":[1,0,0,0,0,1,0,0,0,0,1,0,0,0,0,1],"contentsRect":{"y":0,"x":0,"width":1,"height":1},"opacity":1,"edgeAntialiasingMask":251658240,"height":1080,"hidden":false,"anchorPoint":{"pointX":0.5,"pointY":0.5}},"layers":[{"animations":[],"initialState":{"affineTransform":[1,0,0,1,0,0],"masksToBounds":false,"rotation":0,"scale":1,"position":{"pointX":960,"pointY":165},"width":1654,"sublayerTransform":[1,0,0,0,0,1,0,0,0,0,1,0,0,0,0,1],"contentsRect":{"y":0,"x":0,"width":1,"height":1},"opacity":1,"edgeAntialiasingMask":251658240,"height":180,"hidden":false,"anchorPoint":{"pointX":0.5,"pointY":0.5}},"objectID":"C9F71DE0-E270-493E-A38D-D865A783AA94","layers":[{"animations":[],"layers":[],"initialState":{"affineTransform":[1,0,0,1,0,0],"masksToBounds":false,"rotation":0,"scale":1,"position":{"pointX":829,"pointY":91.5},"width":542,"sublayerTransform":[1,0,0,0,0,1,0,0,0,0,1,0,0,0,0,1],"contentsRect":{"y":0,"x":0,"width":1,"height":1},"opacity":1,"edgeAntialiasingMask":0,"height":85,"hidden":false,"anchorPoint":{"pointX":0.5,"pointY":0.5}},"texture":"CDC5FF49500FCCB406DE3F065BDECC81"}]}]},{"animations":[],"initialState":{"affineTransform":[1,0,0,1,0,0],"masksToBounds":false,"rotation":0,"scale":1,"position":{"pointX":960,"pointY":540},"width":1920,"sublayerTransform":[1,0,0,0,0,1,0,0,0,0,1,0,0,0,0,1],"contentsRect":{"y":0,"x":0,"width":1,"height":1},"opacity":1,"edgeAntialiasingMask":251658240,"height":1080,"hidden":false,"anchorPoint":{"pointX":0.5,"pointY":0.5}},"layers":[{"animations":[],"initialState":{"affineTransform":[1,0,0,1,0,0],"masksToBounds":false,"rotation":0,"scale":1,"position":{"pointX":960,"pointY":617.5},"width":1654,"sublayerTransform":[1,0,0,0,0,1,0,0,0,0,1,0,0,0,0,1],"contentsRect":{"y":0,"x":0,"width":1,"height":1},"opacity":1,"edgeAntialiasingMask":251658240,"height":725,"hidden":false,"anchorPoint":{"pointX":0.5,"pointY":0.5}},"objectID":"FB6CB0C2-F793-4CCB-AE07-F86A6CECF5A9","layers":[{"animations":[],"layers":[],"initialState":{"affineTransform":[1,0,0,1,0,0],"masksToBounds":false,"rotation":0,"scale":1,"position":{"pointX":172,"pointY":35},"width":336,"sublayerTransform":[1,0,0,0,0,1,0,0,0,0,1,0,0,0,0,1],"contentsRect":{"y":0,"x":0,"width":1,"height":1},"opacity":1,"edgeAntialiasingMask":0,"height":42,"hidden":true,"anchorPoint":{"pointX":0.5,"pointY":0.5}},"texture":"0140AD956977053E067D61A2F3E68396"},{"animations":[],"layers":[],"initialState":{"affineTransform":[1,0,0,1,0,0],"masksToBounds":false,"rotation":0,"scale":1,"position":{"pointX":383,"pointY":147.5},"width":758,"sublayerTransform":[1,0,0,0,0,1,0,0,0,0,1,0,0,0,0,1],"contentsRect":{"y":0,"x":0,"width":1,"height":1},"opacity":1,"edgeAntialiasingMask":0,"height":47,"hidden":true,"anchorPoint":{"pointX":0.5,"pointY":0.5}},"texture":"DBA6C240F4FFF39844A44556BE2C2CF7"},{"animations":[],"layers":[],"initialState":{"affineTransform":[1,0,0,1,0,0],"masksToBounds":false,"rotation":0,"scale":1,"position":{"pointX":597.5,"pointY":421.5},"width":1187,"sublayerTransform":[1,0,0,0,0,1,0,0,0,0,1,0,0,0,0,1],"contentsRect":{"y":0,"x":0,"width":1,"height":1},"opacity":1,"edgeAntialiasingMask":0,"height":377,"hidden":true,"anchorPoint":{"pointX":0.5,"pointY":0.5}},"texture":"015F7C12121A4F77FD7EC7C29E1BAA80"},{"animations":[],"layers":[],"initialState":{"affineTransform":[1,0,0,1,0,0],"masksToBounds":false,"rotation":0,"scale":1,"position":{"pointX":531.5,"pointY":696},"width":1055,"sublayerTransform":[1,0,0,0,0,1,0,0,0,0,1,0,0,0,0,1],"contentsRect":{"y":0,"x":0,"width":1,"height":1},"opacity":1,"edgeAntialiasingMask":0,"height":48,"hidden":true,"anchorPoint":{"pointX":0.5,"pointY":0.5}},"texture":"1785A4D437AB25764E6B3795F35A733C"}]}]},{"animations":[],"initialState":{"affineTransform":[1,0,0,1,0,0],"masksToBounds":false,"rotation":0,"scale":1,"position":{"pointX":960,"pointY":540},"width":1920,"sublayerTransform":[1,0,0,0,0,1,0,0,0,0,1,0,0,0,0,1],"contentsRect":{"y":0,"x":0,"width":1,"height":1},"opacity":1,"edgeAntialiasingMask":251658240,"height":1080,"hidden":false,"anchorPoint":{"pointX":0.5,"pointY":0.5}},"layers":[{"animations":[],"initialState":{"affineTransform":[1,0,0,1,0,0],"masksToBounds":false,"rotation":0,"scale":1,"position":{"pointX":1474.616554054055,"pointY":413.9885979729729},"width":772,"sublayerTransform":[1,0,0,0,0,1,0,0,0,0,1,0,0,0,0,1],"contentsRect":{"y":0,"x":0,"width":1,"height":1},"opacity":1,"edgeAntialiasingMask":251658240,"height":301.9999999999999,"hidden":false,"anchorPoint":{"pointX":0.5,"pointY":0.5}},"objectID":"FE480AE0-80EB-4DDA-9725-1C2655EEFDB7","layers":[{"animations":[],"layers":[],"initialState":{"affineTransform":[1,0,0,1,0,0],"masksToBounds":false,"rotation":0,"scale":1,"position":{"pointX":385.8834459459449,"pointY":150.511402027027},"width":785,"sublayerTransform":[1,0,0,0,0,1,0,0,0,0,1,0,0,0,0,1],"contentsRect":{"y":0,"x":0,"width":1,"height":1},"opacity":1,"edgeAntialiasingMask":0,"height":547,"hidden":true,"anchorPoint":{"pointX":0.5,"pointY":0.5}},"texture":"FD5C3ED2E7434E6BDFE9C06C3ED1715E"}]}]}]}},{"effects":[{"beginTime":0,"baseLayer":{"animations":[],"initialState":{"affineTransform":[1,0,0,1,0,0],"masksToBounds":false,"rotation":0,"scale":1,"position":{"pointX":960,"pointY":617.5},"width":1654,"sublayerTransform":[1,0,0,0,0,1,0,0,0,0,1,0,0,0,0,1],"contentsRect":{"y":0,"x":0,"width":1,"height":1},"opacity":1,"edgeAntialiasingMask":251658240,"height":725,"hidden":false,"anchorPoint":{"pointX":0.5,"pointY":0.5}},"objectID":"FB6CB0C2-F793-4CCB-AE07-F86A6CECF5A9","layers":[{"animations":[],"layers":[],"initialState":{"affineTransform":[1,0,0,1,0,0],"masksToBounds":false,"rotation":0,"scale":1,"position":{"pointX":172,"pointY":35},"width":336,"sublayerTransform":[1,0,0,0,0,1,0,0,0,0,1,0,0,0,0,1],"contentsRect":{"y":0,"x":0,"width":1,"height":1},"opacity":1,"edgeAntialiasingMask":0,"height":42,"hidden":false,"anchorPoint":{"pointX":0.5,"pointY":0.5}},"texture":"0140AD956977053E067D61A2F3E68396"},{"animations":[],"initialState":{"affineTransform":[1,0,0,1,0,0],"masksToBounds":false,"rotation":0,"scale":1,"position":{"pointX":827,"pointY":285},"width":1654,"sublayerTransform":[1,0,0,0,0,1,0,0,0,0,1,-0.0003500791246677598,0,0,0,1],"contentsRect":{"y":0,"x":0,"width":1,"height":1},"opacity":1,"edgeAntialiasingMask":251658240,"height":725,"hidden":false,"anchorPoint":{"pointX":0.5,"pointY":0.3931034482758621}},"layers":[{"animations":[{"timeOffset":0,"beginTime":1e-100,"repeatCount":0,"animations":[{"timeOffset":0,"from":{"scalar":0},"beginTime":0,"repeatCount":0,"fillMode":"both","duration":1,"autoreverses":false,"timingFunction":"EaseInEaseOut","property":"opacity","to":{"scalar":1}},{"timeOffset":0,"from":{"scalar":false},"beginTime":0,"repeatCount":0,"fillMode":"forwards","property":"hidden","autoreverses":false,"duration":1,"to":{"scalar":false}}],"fillMode":"both","autoreverses":false,"duration":1}],"layers":[],"initialState":{"affineTransform":[1,0,0,1,0,0],"masksToBounds":false,"rotation":0,"scale":1,"position":{"pointX":383,"pointY":147.5},"width":758,"sublayerTransform":[1,0,0,0,0,1,0,0,0,0,1,0,0,0,0,1],"contentsRect":{"y":0,"x":0,"width":1,"height":1},"opacity":1,"edgeAntialiasingMask":0,"height":47,"hidden":true,"anchorPoint":{"pointX":0.5,"pointY":0.5}},"texture":"DBA6C240F4FFF39844A44556BE2C2CF7"}]},{"animations":[],"layers":[],"initialState":{"affineTransform":[1,0,0,1,0,0],"masksToBounds":false,"rotation":0,"scale":1,"position":{"pointX":597.5,"pointY":421.5},"width":1187,"sublayerTransform":[1,0,0,0,0,1,0,0,0,0,1,0,0,0,0,1],"contentsRect":{"y":0,"x":0,"width":1,"height":1},"opacity":1,"edgeAntialiasingMask":0,"height":377,"hidden":true,"anchorPoint":{"pointX":0.5,"pointY":0.5}},"texture":"015F7C12121A4F77FD7EC7C29E1BAA80"},{"animations":[],"layers":[],"initialState":{"affineTransform":[1,0,0,1,0,0],"masksToBounds":false,"rotation":0,"scale":1,"position":{"pointX":531.5,"pointY":696},"width":1055,"sublayerTransform":[1,0,0,0,0,1,0,0,0,0,1,0,0,0,0,1],"contentsRect":{"y":0,"x":0,"width":1,"height":1},"opacity":1,"edgeAntialiasingMask":0,"height":48,"hidden":true,"anchorPoint":{"pointX":0.5,"pointY":0.5}},"texture":"1785A4D437AB25764E6B3795F35A733C"}]},"effects":[],"duration":1,"type":"buildIn","name":"apple:dissolve character","objectID":"FB6CB0C2-F793-4CCB-AE07-F86A6CECF5A9"}],"automaticPlay":false,"hyperlinks":[],"accessibility":[{"text":"Decorators","targetRectangle":{"y":98,"x":683.024,"width":553.9520000000001,"height":134}},{"text":"Skærmbillede 2016-09-28 kl. 11.42.25.png","targetRectangle":{"y":262.988597972973,"x":1088.616554054055,"width":772,"height":301.9999999999999}},{"text":"I feared these","targetRectangle":{"y":260,"x":182.4999984047963,"width":291.11264,"height":56}}],"baseLayer":{"animations":[],"initialState":{"affineTransform":[1,0,0,1,0,0],"masksToBounds":false,"rotation":0,"scale":1,"position":{"pointX":960,"pointY":540},"width":1920,"sublayerTransform":[1,0,0,0,0,1,0,0,0,0,1,0,0,0,0,1],"contentsRect":{"y":0,"x":0,"width":1,"height":1},"opacity":1,"edgeAntialiasingMask":251658240,"height":1080,"hidden":false,"anchorPoint":{"pointX":0.5,"pointY":0.5}},"layers":[{"animations":[],"initialState":{"affineTransform":[1,0,0,1,0,0],"masksToBounds":false,"rotation":0,"scale":1,"position":{"pointX":960,"pointY":540},"width":1920,"sublayerTransform":[1,0,0,0,0,1,0,0,0,0,1,0,0,0,0,1],"contentsRect":{"y":0,"x":0,"width":1,"height":1},"opacity":1,"edgeAntialiasingMask":251658240,"height":1080,"hidden":false,"anchorPoint":{"pointX":0.5,"pointY":0.5}},"layers":[{"animations":[],"initialState":{"affineTransform":[1,0,0,1,0,0],"masksToBounds":false,"rotation":0,"scale":1,"position":{"pointX":960,"pointY":540},"width":1920,"sublayerTransform":[1,0,0,0,0,1,0,0,0,0,1,0,0,0,0,1],"contentsRect":{"y":0,"x":0,"width":1,"height":1},"opacity":1,"edgeAntialiasingMask":251658240,"height":1080,"hidden":false,"anchorPoint":{"pointX":0.5,"pointY":0.5}},"layers":[{"animations":[],"layers":[],"initialState":{"affineTransform":[1,0,0,1,0,0],"masksToBounds":false,"rotation":0,"scale":1,"position":{"pointX":960,"pointY":540},"width":1920,"sublayerTransform":[1,0,0,0,0,1,0,0,0,0,1,0,0,0,0,1],"contentsRect":{"y":0,"x":0,"width":1,"height":1},"opacity":1,"edgeAntialiasingMask":0,"height":1080,"hidden":false,"anchorPoint":{"pointX":0.5,"pointY":0.5}},"texture":"C25C25FF361FB24FC35F6B120D2F252D"}]}]},{"animations":[],"initialState":{"affineTransform":[1,0,0,1,0,0],"masksToBounds":false,"rotation":0,"scale":1,"position":{"pointX":960,"pointY":540},"width":1920,"sublayerTransform":[1,0,0,0,0,1,0,0,0,0,1,0,0,0,0,1],"contentsRect":{"y":0,"x":0,"width":1,"height":1},"opacity":1,"edgeAntialiasingMask":251658240,"height":1080,"hidden":false,"anchorPoint":{"pointX":0.5,"pointY":0.5}},"layers":[{"animations":[],"initialState":{"affineTransform":[1,0,0,1,0,0],"masksToBounds":false,"rotation":0,"scale":1,"position":{"pointX":960,"pointY":165},"width":1654,"sublayerTransform":[1,0,0,0,0,1,0,0,0,0,1,0,0,0,0,1],"contentsRect":{"y":0,"x":0,"width":1,"height":1},"opacity":1,"edgeAntialiasingMask":251658240,"height":180,"hidden":false,"anchorPoint":{"pointX":0.5,"pointY":0.5}},"objectID":"C9F71DE0-E270-493E-A38D-D865A783AA94","layers":[{"animations":[],"layers":[],"initialState":{"affineTransform":[1,0,0,1,0,0],"masksToBounds":false,"rotation":0,"scale":1,"position":{"pointX":829,"pointY":91.5},"width":542,"sublayerTransform":[1,0,0,0,0,1,0,0,0,0,1,0,0,0,0,1],"contentsRect":{"y":0,"x":0,"width":1,"height":1},"opacity":1,"edgeAntialiasingMask":0,"height":85,"hidden":false,"anchorPoint":{"pointX":0.5,"pointY":0.5}},"texture":"CDC5FF49500FCCB406DE3F065BDECC81"}]}]},{"animations":[],"initialState":{"affineTransform":[1,0,0,1,0,0],"masksToBounds":false,"rotation":0,"scale":1,"position":{"pointX":960,"pointY":540},"width":1920,"sublayerTransform":[1,0,0,0,0,1,0,0,0,0,1,0,0,0,0,1],"contentsRect":{"y":0,"x":0,"width":1,"height":1},"opacity":1,"edgeAntialiasingMask":251658240,"height":1080,"hidden":false,"anchorPoint":{"pointX":0.5,"pointY":0.5}},"layers":[{"animations":[],"initialState":{"affineTransform":[1,0,0,1,0,0],"masksToBounds":false,"rotation":0,"scale":1,"position":{"pointX":960,"pointY":617.5},"width":1654,"sublayerTransform":[1,0,0,0,0,1,0,0,0,0,1,0,0,0,0,1],"contentsRect":{"y":0,"x":0,"width":1,"height":1},"opacity":1,"edgeAntialiasingMask":251658240,"height":725,"hidden":false,"anchorPoint":{"pointX":0.5,"pointY":0.5}},"objectID":"FB6CB0C2-F793-4CCB-AE07-F86A6CECF5A9","layers":[{"animations":[],"layers":[],"initialState":{"affineTransform":[1,0,0,1,0,0],"masksToBounds":false,"rotation":0,"scale":1,"position":{"pointX":172,"pointY":35},"width":336,"sublayerTransform":[1,0,0,0,0,1,0,0,0,0,1,0,0,0,0,1],"contentsRect":{"y":0,"x":0,"width":1,"height":1},"opacity":1,"edgeAntialiasingMask":0,"height":42,"hidden":false,"anchorPoint":{"pointX":0.5,"pointY":0.5}},"texture":"0140AD956977053E067D61A2F3E68396"},{"animations":[],"layers":[],"initialState":{"affineTransform":[1,0,0,1,0,0],"masksToBounds":false,"rotation":0,"scale":1,"position":{"pointX":383,"pointY":147.5},"width":758,"sublayerTransform":[1,0,0,0,0,1,0,0,0,0,1,0,0,0,0,1],"contentsRect":{"y":0,"x":0,"width":1,"height":1},"opacity":1,"edgeAntialiasingMask":0,"height":47,"hidden":true,"anchorPoint":{"pointX":0.5,"pointY":0.5}},"texture":"DBA6C240F4FFF39844A44556BE2C2CF7"},{"animations":[],"layers":[],"initialState":{"affineTransform":[1,0,0,1,0,0],"masksToBounds":false,"rotation":0,"scale":1,"position":{"pointX":597.5,"pointY":421.5},"width":1187,"sublayerTransform":[1,0,0,0,0,1,0,0,0,0,1,0,0,0,0,1],"contentsRect":{"y":0,"x":0,"width":1,"height":1},"opacity":1,"edgeAntialiasingMask":0,"height":377,"hidden":true,"anchorPoint":{"pointX":0.5,"pointY":0.5}},"texture":"015F7C12121A4F77FD7EC7C29E1BAA80"},{"animations":[],"layers":[],"initialState":{"affineTransform":[1,0,0,1,0,0],"masksToBounds":false,"rotation":0,"scale":1,"position":{"pointX":531.5,"pointY":696},"width":1055,"sublayerTransform":[1,0,0,0,0,1,0,0,0,0,1,0,0,0,0,1],"contentsRect":{"y":0,"x":0,"width":1,"height":1},"opacity":1,"edgeAntialiasingMask":0,"height":48,"hidden":true,"anchorPoint":{"pointX":0.5,"pointY":0.5}},"texture":"1785A4D437AB25764E6B3795F35A733C"}]}]},{"animations":[],"initialState":{"affineTransform":[1,0,0,1,0,0],"masksToBounds":false,"rotation":0,"scale":1,"position":{"pointX":960,"pointY":540},"width":1920,"sublayerTransform":[1,0,0,0,0,1,0,0,0,0,1,0,0,0,0,1],"contentsRect":{"y":0,"x":0,"width":1,"height":1},"opacity":1,"edgeAntialiasingMask":251658240,"height":1080,"hidden":false,"anchorPoint":{"pointX":0.5,"pointY":0.5}},"layers":[{"animations":[],"initialState":{"affineTransform":[1,0,0,1,0,0],"masksToBounds":false,"rotation":0,"scale":1,"position":{"pointX":1474.616554054055,"pointY":413.9885979729729},"width":772,"sublayerTransform":[1,0,0,0,0,1,0,0,0,0,1,0,0,0,0,1],"contentsRect":{"y":0,"x":0,"width":1,"height":1},"opacity":1,"edgeAntialiasingMask":251658240,"height":301.9999999999999,"hidden":false,"anchorPoint":{"pointX":0.5,"pointY":0.5}},"objectID":"FE480AE0-80EB-4DDA-9725-1C2655EEFDB7","layers":[{"animations":[],"layers":[],"initialState":{"affineTransform":[1,0,0,1,0,0],"masksToBounds":false,"rotation":0,"scale":1,"position":{"pointX":385.8834459459449,"pointY":150.511402027027},"width":785,"sublayerTransform":[1,0,0,0,0,1,0,0,0,0,1,0,0,0,0,1],"contentsRect":{"y":0,"x":0,"width":1,"height":1},"opacity":1,"edgeAntialiasingMask":0,"height":547,"hidden":false,"anchorPoint":{"pointX":0.5,"pointY":0.5}},"texture":"FD5C3ED2E7434E6BDFE9C06C3ED1715E"}]}]}]}},{"effects":[{"beginTime":0,"baseLayer":{"animations":[],"initialState":{"affineTransform":[1,0,0,1,0,0],"masksToBounds":false,"rotation":0,"scale":1,"position":{"pointX":960,"pointY":617.5},"width":1654,"sublayerTransform":[1,0,0,0,0,1,0,0,0,0,1,0,0,0,0,1],"contentsRect":{"y":0,"x":0,"width":1,"height":1},"opacity":1,"edgeAntialiasingMask":251658240,"height":725,"hidden":false,"anchorPoint":{"pointX":0.5,"pointY":0.5}},"objectID":"FB6CB0C2-F793-4CCB-AE07-F86A6CECF5A9","layers":[{"animations":[],"layers":[],"initialState":{"affineTransform":[1,0,0,1,0,0],"masksToBounds":false,"rotation":0,"scale":1,"position":{"pointX":172,"pointY":35},"width":336,"sublayerTransform":[1,0,0,0,0,1,0,0,0,0,1,0,0,0,0,1],"contentsRect":{"y":0,"x":0,"width":1,"height":1},"opacity":1,"edgeAntialiasingMask":0,"height":42,"hidden":false,"anchorPoint":{"pointX":0.5,"pointY":0.5}},"texture":"0140AD956977053E067D61A2F3E68396"},{"animations":[],"layers":[],"initialState":{"affineTransform":[1,0,0,1,0,0],"masksToBounds":false,"rotation":0,"scale":1,"position":{"pointX":383,"pointY":147.5},"width":758,"sublayerTransform":[1,0,0,0,0,1,0,0,0,0,1,0,0,0,0,1],"contentsRect":{"y":0,"x":0,"width":1,"height":1},"opacity":1,"edgeAntialiasingMask":0,"height":47,"hidden":false,"anchorPoint":{"pointX":0.5,"pointY":0.5}},"texture":"DBA6C240F4FFF39844A44556BE2C2CF7"},{"animations":[],"initialState":{"affineTransform":[1,0,0,1,0,0],"masksToBounds":false,"rotation":0,"scale":1,"position":{"pointX":827,"pointY":285},"width":1654,"sublayerTransform":[1,0,0,0,0,1,0,0,0,0,1,-0.0003500791246677598,0,0,0,1],"contentsRect":{"y":0,"x":0,"width":1,"height":1},"opacity":1,"edgeAntialiasingMask":251658240,"height":725,"hidden":false,"anchorPoint":{"pointX":0.5,"pointY":0.3931034482758621}},"layers":[{"animations":[{"timeOffset":0,"beginTime":1e-100,"repeatCount":0,"animations":[{"timeOffset":0,"from":{"scalar":0},"beginTime":0,"repeatCount":0,"fillMode":"both","duration":1,"autoreverses":false,"timingFunction":"EaseInEaseOut","property":"opacity","to":{"scalar":1}},{"timeOffset":0,"from":{"scalar":false},"beginTime":0,"repeatCount":0,"fillMode":"forwards","property":"hidden","autoreverses":false,"duration":1,"to":{"scalar":false}}],"fillMode":"both","autoreverses":false,"duration":1}],"layers":[],"initialState":{"affineTransform":[1,0,0,1,0,0],"masksToBounds":false,"rotation":0,"scale":1,"position":{"pointX":597.5,"pointY":421.5},"width":1187,"sublayerTransform":[1,0,0,0,0,1,0,0,0,0,1,0,0,0,0,1],"contentsRect":{"y":0,"x":0,"width":1,"height":1},"opacity":1,"edgeAntialiasingMask":0,"height":377,"hidden":true,"anchorPoint":{"pointX":0.5,"pointY":0.5}},"texture":"015F7C12121A4F77FD7EC7C29E1BAA80"}]},{"animations":[],"layers":[],"initialState":{"affineTransform":[1,0,0,1,0,0],"masksToBounds":false,"rotation":0,"scale":1,"position":{"pointX":531.5,"pointY":696},"width":1055,"sublayerTransform":[1,0,0,0,0,1,0,0,0,0,1,0,0,0,0,1],"contentsRect":{"y":0,"x":0,"width":1,"height":1},"opacity":1,"edgeAntialiasingMask":0,"height":48,"hidden":true,"anchorPoint":{"pointX":0.5,"pointY":0.5}},"texture":"1785A4D437AB25764E6B3795F35A733C"}]},"effects":[],"duration":1,"type":"buildIn","name":"apple:dissolve character","objectID":"FB6CB0C2-F793-4CCB-AE07-F86A6CECF5A9"}],"automaticPlay":false,"hyperlinks":[],"accessibility":[{"text":"Decorators","targetRectangle":{"y":98,"x":683.024,"width":553.9520000000001,"height":134}},{"text":"Skærmbillede 2016-09-28 kl. 11.42.25.png","targetRectangle":{"y":262.988597972973,"x":1088.616554054055,"width":772,"height":301.9999999999999}},{"text":"I feared these","targetRectangle":{"y":260,"x":182.4999984047963,"width":291.11264,"height":56}},{"text":"Turns out that they work quite well","targetRectangle":{"y":316,"x":182.4999984047963,"width":714.48468,"height":109.6900015473366}}],"baseLayer":{"animations":[],"initialState":{"affineTransform":[1,0,0,1,0,0],"masksToBounds":false,"rotation":0,"scale":1,"position":{"pointX":960,"pointY":540},"width":1920,"sublayerTransform":[1,0,0,0,0,1,0,0,0,0,1,0,0,0,0,1],"contentsRect":{"y":0,"x":0,"width":1,"height":1},"opacity":1,"edgeAntialiasingMask":251658240,"height":1080,"hidden":false,"anchorPoint":{"pointX":0.5,"pointY":0.5}},"layers":[{"animations":[],"initialState":{"affineTransform":[1,0,0,1,0,0],"masksToBounds":false,"rotation":0,"scale":1,"position":{"pointX":960,"pointY":540},"width":1920,"sublayerTransform":[1,0,0,0,0,1,0,0,0,0,1,0,0,0,0,1],"contentsRect":{"y":0,"x":0,"width":1,"height":1},"opacity":1,"edgeAntialiasingMask":251658240,"height":1080,"hidden":false,"anchorPoint":{"pointX":0.5,"pointY":0.5}},"layers":[{"animations":[],"initialState":{"affineTransform":[1,0,0,1,0,0],"masksToBounds":false,"rotation":0,"scale":1,"position":{"pointX":960,"pointY":540},"width":1920,"sublayerTransform":[1,0,0,0,0,1,0,0,0,0,1,0,0,0,0,1],"contentsRect":{"y":0,"x":0,"width":1,"height":1},"opacity":1,"edgeAntialiasingMask":251658240,"height":1080,"hidden":false,"anchorPoint":{"pointX":0.5,"pointY":0.5}},"layers":[{"animations":[],"layers":[],"initialState":{"affineTransform":[1,0,0,1,0,0],"masksToBounds":false,"rotation":0,"scale":1,"position":{"pointX":960,"pointY":540},"width":1920,"sublayerTransform":[1,0,0,0,0,1,0,0,0,0,1,0,0,0,0,1],"contentsRect":{"y":0,"x":0,"width":1,"height":1},"opacity":1,"edgeAntialiasingMask":0,"height":1080,"hidden":false,"anchorPoint":{"pointX":0.5,"pointY":0.5}},"texture":"C25C25FF361FB24FC35F6B120D2F252D"}]}]},{"animations":[],"initialState":{"affineTransform":[1,0,0,1,0,0],"masksToBounds":false,"rotation":0,"scale":1,"position":{"pointX":960,"pointY":540},"width":1920,"sublayerTransform":[1,0,0,0,0,1,0,0,0,0,1,0,0,0,0,1],"contentsRect":{"y":0,"x":0,"width":1,"height":1},"opacity":1,"edgeAntialiasingMask":251658240,"height":1080,"hidden":false,"anchorPoint":{"pointX":0.5,"pointY":0.5}},"layers":[{"animations":[],"initialState":{"affineTransform":[1,0,0,1,0,0],"masksToBounds":false,"rotation":0,"scale":1,"position":{"pointX":960,"pointY":165},"width":1654,"sublayerTransform":[1,0,0,0,0,1,0,0,0,0,1,0,0,0,0,1],"contentsRect":{"y":0,"x":0,"width":1,"height":1},"opacity":1,"edgeAntialiasingMask":251658240,"height":180,"hidden":false,"anchorPoint":{"pointX":0.5,"pointY":0.5}},"objectID":"C9F71DE0-E270-493E-A38D-D865A783AA94","layers":[{"animations":[],"layers":[],"initialState":{"affineTransform":[1,0,0,1,0,0],"masksToBounds":false,"rotation":0,"scale":1,"position":{"pointX":829,"pointY":91.5},"width":542,"sublayerTransform":[1,0,0,0,0,1,0,0,0,0,1,0,0,0,0,1],"contentsRect":{"y":0,"x":0,"width":1,"height":1},"opacity":1,"edgeAntialiasingMask":0,"height":85,"hidden":false,"anchorPoint":{"pointX":0.5,"pointY":0.5}},"texture":"CDC5FF49500FCCB406DE3F065BDECC81"}]}]},{"animations":[],"initialState":{"affineTransform":[1,0,0,1,0,0],"masksToBounds":false,"rotation":0,"scale":1,"position":{"pointX":960,"pointY":540},"width":1920,"sublayerTransform":[1,0,0,0,0,1,0,0,0,0,1,0,0,0,0,1],"contentsRect":{"y":0,"x":0,"width":1,"height":1},"opacity":1,"edgeAntialiasingMask":251658240,"height":1080,"hidden":false,"anchorPoint":{"pointX":0.5,"pointY":0.5}},"layers":[{"animations":[],"initialState":{"affineTransform":[1,0,0,1,0,0],"masksToBounds":false,"rotation":0,"scale":1,"position":{"pointX":960,"pointY":617.5},"width":1654,"sublayerTransform":[1,0,0,0,0,1,0,0,0,0,1,0,0,0,0,1],"contentsRect":{"y":0,"x":0,"width":1,"height":1},"opacity":1,"edgeAntialiasingMask":251658240,"height":725,"hidden":false,"anchorPoint":{"pointX":0.5,"pointY":0.5}},"objectID":"FB6CB0C2-F793-4CCB-AE07-F86A6CECF5A9","layers":[{"animations":[],"layers":[],"initialState":{"affineTransform":[1,0,0,1,0,0],"masksToBounds":false,"rotation":0,"scale":1,"position":{"pointX":172,"pointY":35},"width":336,"sublayerTransform":[1,0,0,0,0,1,0,0,0,0,1,0,0,0,0,1],"contentsRect":{"y":0,"x":0,"width":1,"height":1},"opacity":1,"edgeAntialiasingMask":0,"height":42,"hidden":false,"anchorPoint":{"pointX":0.5,"pointY":0.5}},"texture":"0140AD956977053E067D61A2F3E68396"},{"animations":[],"layers":[],"initialState":{"affineTransform":[1,0,0,1,0,0],"masksToBounds":false,"rotation":0,"scale":1,"position":{"pointX":383,"pointY":147.5},"width":758,"sublayerTransform":[1,0,0,0,0,1,0,0,0,0,1,0,0,0,0,1],"contentsRect":{"y":0,"x":0,"width":1,"height":1},"opacity":1,"edgeAntialiasingMask":0,"height":47,"hidden":false,"anchorPoint":{"pointX":0.5,"pointY":0.5}},"texture":"DBA6C240F4FFF39844A44556BE2C2CF7"},{"animations":[],"layers":[],"initialState":{"affineTransform":[1,0,0,1,0,0],"masksToBounds":false,"rotation":0,"scale":1,"position":{"pointX":597.5,"pointY":421.5},"width":1187,"sublayerTransform":[1,0,0,0,0,1,0,0,0,0,1,0,0,0,0,1],"contentsRect":{"y":0,"x":0,"width":1,"height":1},"opacity":1,"edgeAntialiasingMask":0,"height":377,"hidden":true,"anchorPoint":{"pointX":0.5,"pointY":0.5}},"texture":"015F7C12121A4F77FD7EC7C29E1BAA80"},{"animations":[],"layers":[],"initialState":{"affineTransform":[1,0,0,1,0,0],"masksToBounds":false,"rotation":0,"scale":1,"position":{"pointX":531.5,"pointY":696},"width":1055,"sublayerTransform":[1,0,0,0,0,1,0,0,0,0,1,0,0,0,0,1],"contentsRect":{"y":0,"x":0,"width":1,"height":1},"opacity":1,"edgeAntialiasingMask":0,"height":48,"hidden":true,"anchorPoint":{"pointX":0.5,"pointY":0.5}},"texture":"1785A4D437AB25764E6B3795F35A733C"}]}]},{"animations":[],"initialState":{"affineTransform":[1,0,0,1,0,0],"masksToBounds":false,"rotation":0,"scale":1,"position":{"pointX":960,"pointY":540},"width":1920,"sublayerTransform":[1,0,0,0,0,1,0,0,0,0,1,0,0,0,0,1],"contentsRect":{"y":0,"x":0,"width":1,"height":1},"opacity":1,"edgeAntialiasingMask":251658240,"height":1080,"hidden":false,"anchorPoint":{"pointX":0.5,"pointY":0.5}},"layers":[{"animations":[],"initialState":{"affineTransform":[1,0,0,1,0,0],"masksToBounds":false,"rotation":0,"scale":1,"position":{"pointX":1474.616554054055,"pointY":413.9885979729729},"width":772,"sublayerTransform":[1,0,0,0,0,1,0,0,0,0,1,0,0,0,0,1],"contentsRect":{"y":0,"x":0,"width":1,"height":1},"opacity":1,"edgeAntialiasingMask":251658240,"height":301.9999999999999,"hidden":false,"anchorPoint":{"pointX":0.5,"pointY":0.5}},"objectID":"FE480AE0-80EB-4DDA-9725-1C2655EEFDB7","layers":[{"animations":[],"layers":[],"initialState":{"affineTransform":[1,0,0,1,0,0],"masksToBounds":false,"rotation":0,"scale":1,"position":{"pointX":385.8834459459449,"pointY":150.511402027027},"width":785,"sublayerTransform":[1,0,0,0,0,1,0,0,0,0,1,0,0,0,0,1],"contentsRect":{"y":0,"x":0,"width":1,"height":1},"opacity":1,"edgeAntialiasingMask":0,"height":547,"hidden":false,"anchorPoint":{"pointX":0.5,"pointY":0.5}},"texture":"FD5C3ED2E7434E6BDFE9C06C3ED1715E"}]}]}]}},{"effects":[{"beginTime":0,"baseLayer":{"animations":[],"initialState":{"affineTransform":[1,0,0,1,0,0],"masksToBounds":false,"rotation":0,"scale":1,"position":{"pointX":960,"pointY":617.5},"width":1654,"sublayerTransform":[1,0,0,0,0,1,0,0,0,0,1,0,0,0,0,1],"contentsRect":{"y":0,"x":0,"width":1,"height":1},"opacity":1,"edgeAntialiasingMask":251658240,"height":725,"hidden":false,"anchorPoint":{"pointX":0.5,"pointY":0.5}},"objectID":"FB6CB0C2-F793-4CCB-AE07-F86A6CECF5A9","layers":[{"animations":[],"layers":[],"initialState":{"affineTransform":[1,0,0,1,0,0],"masksToBounds":false,"rotation":0,"scale":1,"position":{"pointX":172,"pointY":35},"width":336,"sublayerTransform":[1,0,0,0,0,1,0,0,0,0,1,0,0,0,0,1],"contentsRect":{"y":0,"x":0,"width":1,"height":1},"opacity":1,"edgeAntialiasingMask":0,"height":42,"hidden":false,"anchorPoint":{"pointX":0.5,"pointY":0.5}},"texture":"0140AD956977053E067D61A2F3E68396"},{"animations":[],"layers":[],"initialState":{"affineTransform":[1,0,0,1,0,0],"masksToBounds":false,"rotation":0,"scale":1,"position":{"pointX":383,"pointY":147.5},"width":758,"sublayerTransform":[1,0,0,0,0,1,0,0,0,0,1,0,0,0,0,1],"contentsRect":{"y":0,"x":0,"width":1,"height":1},"opacity":1,"edgeAntialiasingMask":0,"height":47,"hidden":false,"anchorPoint":{"pointX":0.5,"pointY":0.5}},"texture":"DBA6C240F4FFF39844A44556BE2C2CF7"},{"animations":[],"layers":[],"initialState":{"affineTransform":[1,0,0,1,0,0],"masksToBounds":false,"rotation":0,"scale":1,"position":{"pointX":597.5,"pointY":421.5},"width":1187,"sublayerTransform":[1,0,0,0,0,1,0,0,0,0,1,0,0,0,0,1],"contentsRect":{"y":0,"x":0,"width":1,"height":1},"opacity":1,"edgeAntialiasingMask":0,"height":377,"hidden":false,"anchorPoint":{"pointX":0.5,"pointY":0.5}},"texture":"015F7C12121A4F77FD7EC7C29E1BAA80"},{"animations":[],"initialState":{"affineTransform":[1,0,0,1,0,0],"masksToBounds":false,"rotation":0,"scale":1,"position":{"pointX":827,"pointY":285},"width":1654,"sublayerTransform":[1,0,0,0,0,1,0,0,0,0,1,-0.0003500791246677598,0,0,0,1],"contentsRect":{"y":0,"x":0,"width":1,"height":1},"opacity":1,"edgeAntialiasingMask":251658240,"height":725,"hidden":false,"anchorPoint":{"pointX":0.5,"pointY":0.3931034482758621}},"layers":[{"animations":[{"timeOffset":0,"beginTime":1e-100,"repeatCount":0,"animations":[{"timeOffset":0,"from":{"scalar":0},"beginTime":0,"repeatCount":0,"fillMode":"both","duration":1,"autoreverses":false,"timingFunction":"EaseInEaseOut","property":"opacity","to":{"scalar":1}},{"timeOffset":0,"from":{"scalar":false},"beginTime":0,"repeatCount":0,"fillMode":"forwards","property":"hidden","autoreverses":false,"duration":1,"to":{"scalar":false}}],"fillMode":"both","autoreverses":false,"duration":1}],"layers":[],"initialState":{"affineTransform":[1,0,0,1,0,0],"masksToBounds":false,"rotation":0,"scale":1,"position":{"pointX":531.5,"pointY":696},"width":1055,"sublayerTransform":[1,0,0,0,0,1,0,0,0,0,1,0,0,0,0,1],"contentsRect":{"y":0,"x":0,"width":1,"height":1},"opacity":1,"edgeAntialiasingMask":0,"height":48,"hidden":true,"anchorPoint":{"pointX":0.5,"pointY":0.5}},"texture":"1785A4D437AB25764E6B3795F35A733C"}]}]},"effects":[],"duration":1,"type":"buildIn","name":"apple:dissolve character","objectID":"FB6CB0C2-F793-4CCB-AE07-F86A6CECF5A9"}],"automaticPlay":false,"hyperlinks":[],"accessibility":[{"text":"Decorators","targetRectangle":{"y":98,"x":683.024,"width":553.9520000000001,"height":134}},{"text":"Skærmbillede 2016-09-28 kl. 11.42.25.png","targetRectangle":{"y":262.988597972973,"x":1088.616554054055,"width":772,"height":301.9999999999999}},{"text":"I feared these","targetRectangle":{"y":260,"x":182.4999984047963,"width":291.11264,"height":56}},{"text":"Turns out that they work quite well","targetRectangle":{"y":316,"x":182.4999984047963,"width":714.48468,"height":109.6900015473366}},{"text":"Prefixed with an @","targetRectangle":{"y":425.6900015473366,"x":182.4999984047963,"width":386.74636,"height":109.6900015473366}},{"text":"@Injectable() -> Service","targetRectangle":{"y":535.3800030946732,"x":232.4999984047963,"width":508.2168,"height":109.6900015473366}},{"text":"@Component() -> Component","targetRectangle":{"y":645.0700046420097,"x":232.4999984047963,"width":637.0691600000001,"height":109.6900015473366}},{"text":"@ngModule() -> Only used for app module in demo","targetRectangle":{"y":754.7600061893463,"x":232.4999984047963,"width":1091.95632,"height":109.6900015473366}}],"baseLayer":{"animations":[],"initialState":{"affineTransform":[1,0,0,1,0,0],"masksToBounds":false,"rotation":0,"scale":1,"position":{"pointX":960,"pointY":540},"width":1920,"sublayerTransform":[1,0,0,0,0,1,0,0,0,0,1,0,0,0,0,1],"contentsRect":{"y":0,"x":0,"width":1,"height":1},"opacity":1,"edgeAntialiasingMask":251658240,"height":1080,"hidden":false,"anchorPoint":{"pointX":0.5,"pointY":0.5}},"layers":[{"animations":[],"initialState":{"affineTransform":[1,0,0,1,0,0],"masksToBounds":false,"rotation":0,"scale":1,"position":{"pointX":960,"pointY":540},"width":1920,"sublayerTransform":[1,0,0,0,0,1,0,0,0,0,1,0,0,0,0,1],"contentsRect":{"y":0,"x":0,"width":1,"height":1},"opacity":1,"edgeAntialiasingMask":251658240,"height":1080,"hidden":false,"anchorPoint":{"pointX":0.5,"pointY":0.5}},"layers":[{"animations":[],"initialState":{"affineTransform":[1,0,0,1,0,0],"masksToBounds":false,"rotation":0,"scale":1,"position":{"pointX":960,"pointY":540},"width":1920,"sublayerTransform":[1,0,0,0,0,1,0,0,0,0,1,0,0,0,0,1],"contentsRect":{"y":0,"x":0,"width":1,"height":1},"opacity":1,"edgeAntialiasingMask":251658240,"height":1080,"hidden":false,"anchorPoint":{"pointX":0.5,"pointY":0.5}},"layers":[{"animations":[],"layers":[],"initialState":{"affineTransform":[1,0,0,1,0,0],"masksToBounds":false,"rotation":0,"scale":1,"position":{"pointX":960,"pointY":540},"width":1920,"sublayerTransform":[1,0,0,0,0,1,0,0,0,0,1,0,0,0,0,1],"contentsRect":{"y":0,"x":0,"width":1,"height":1},"opacity":1,"edgeAntialiasingMask":0,"height":1080,"hidden":false,"anchorPoint":{"pointX":0.5,"pointY":0.5}},"texture":"C25C25FF361FB24FC35F6B120D2F252D"}]}]},{"animations":[],"initialState":{"affineTransform":[1,0,0,1,0,0],"masksToBounds":false,"rotation":0,"scale":1,"position":{"pointX":960,"pointY":540},"width":1920,"sublayerTransform":[1,0,0,0,0,1,0,0,0,0,1,0,0,0,0,1],"contentsRect":{"y":0,"x":0,"width":1,"height":1},"opacity":1,"edgeAntialiasingMask":251658240,"height":1080,"hidden":false,"anchorPoint":{"pointX":0.5,"pointY":0.5}},"layers":[{"animations":[],"initialState":{"affineTransform":[1,0,0,1,0,0],"masksToBounds":false,"rotation":0,"scale":1,"position":{"pointX":960,"pointY":165},"width":1654,"sublayerTransform":[1,0,0,0,0,1,0,0,0,0,1,0,0,0,0,1],"contentsRect":{"y":0,"x":0,"width":1,"height":1},"opacity":1,"edgeAntialiasingMask":251658240,"height":180,"hidden":false,"anchorPoint":{"pointX":0.5,"pointY":0.5}},"objectID":"C9F71DE0-E270-493E-A38D-D865A783AA94","layers":[{"animations":[],"layers":[],"initialState":{"affineTransform":[1,0,0,1,0,0],"masksToBounds":false,"rotation":0,"scale":1,"position":{"pointX":829,"pointY":91.5},"width":542,"sublayerTransform":[1,0,0,0,0,1,0,0,0,0,1,0,0,0,0,1],"contentsRect":{"y":0,"x":0,"width":1,"height":1},"opacity":1,"edgeAntialiasingMask":0,"height":85,"hidden":false,"anchorPoint":{"pointX":0.5,"pointY":0.5}},"texture":"CDC5FF49500FCCB406DE3F065BDECC81"}]}]},{"animations":[],"initialState":{"affineTransform":[1,0,0,1,0,0],"masksToBounds":false,"rotation":0,"scale":1,"position":{"pointX":960,"pointY":540},"width":1920,"sublayerTransform":[1,0,0,0,0,1,0,0,0,0,1,0,0,0,0,1],"contentsRect":{"y":0,"x":0,"width":1,"height":1},"opacity":1,"edgeAntialiasingMask":251658240,"height":1080,"hidden":false,"anchorPoint":{"pointX":0.5,"pointY":0.5}},"layers":[{"animations":[],"initialState":{"affineTransform":[1,0,0,1,0,0],"masksToBounds":false,"rotation":0,"scale":1,"position":{"pointX":960,"pointY":617.5},"width":1654,"sublayerTransform":[1,0,0,0,0,1,0,0,0,0,1,0,0,0,0,1],"contentsRect":{"y":0,"x":0,"width":1,"height":1},"opacity":1,"edgeAntialiasingMask":251658240,"height":725,"hidden":false,"anchorPoint":{"pointX":0.5,"pointY":0.5}},"objectID":"FB6CB0C2-F793-4CCB-AE07-F86A6CECF5A9","layers":[{"animations":[],"layers":[],"initialState":{"affineTransform":[1,0,0,1,0,0],"masksToBounds":false,"rotation":0,"scale":1,"position":{"pointX":172,"pointY":35},"width":336,"sublayerTransform":[1,0,0,0,0,1,0,0,0,0,1,0,0,0,0,1],"contentsRect":{"y":0,"x":0,"width":1,"height":1},"opacity":1,"edgeAntialiasingMask":0,"height":42,"hidden":false,"anchorPoint":{"pointX":0.5,"pointY":0.5}},"texture":"0140AD956977053E067D61A2F3E68396"},{"animations":[],"layers":[],"initialState":{"affineTransform":[1,0,0,1,0,0],"masksToBounds":false,"rotation":0,"scale":1,"position":{"pointX":383,"pointY":147.5},"width":758,"sublayerTransform":[1,0,0,0,0,1,0,0,0,0,1,0,0,0,0,1],"contentsRect":{"y":0,"x":0,"width":1,"height":1},"opacity":1,"edgeAntialiasingMask":0,"height":47,"hidden":false,"anchorPoint":{"pointX":0.5,"pointY":0.5}},"texture":"DBA6C240F4FFF39844A44556BE2C2CF7"},{"animations":[],"layers":[],"initialState":{"affineTransform":[1,0,0,1,0,0],"masksToBounds":false,"rotation":0,"scale":1,"position":{"pointX":597.5,"pointY":421.5},"width":1187,"sublayerTransform":[1,0,0,0,0,1,0,0,0,0,1,0,0,0,0,1],"contentsRect":{"y":0,"x":0,"width":1,"height":1},"opacity":1,"edgeAntialiasingMask":0,"height":377,"hidden":false,"anchorPoint":{"pointX":0.5,"pointY":0.5}},"texture":"015F7C12121A4F77FD7EC7C29E1BAA80"},{"animations":[],"layers":[],"initialState":{"affineTransform":[1,0,0,1,0,0],"masksToBounds":false,"rotation":0,"scale":1,"position":{"pointX":531.5,"pointY":696},"width":1055,"sublayerTransform":[1,0,0,0,0,1,0,0,0,0,1,0,0,0,0,1],"contentsRect":{"y":0,"x":0,"width":1,"height":1},"opacity":1,"edgeAntialiasingMask":0,"height":48,"hidden":true,"anchorPoint":{"pointX":0.5,"pointY":0.5}},"texture":"1785A4D437AB25764E6B3795F35A733C"}]}]},{"animations":[],"initialState":{"affineTransform":[1,0,0,1,0,0],"masksToBounds":false,"rotation":0,"scale":1,"position":{"pointX":960,"pointY":540},"width":1920,"sublayerTransform":[1,0,0,0,0,1,0,0,0,0,1,0,0,0,0,1],"contentsRect":{"y":0,"x":0,"width":1,"height":1},"opacity":1,"edgeAntialiasingMask":251658240,"height":1080,"hidden":false,"anchorPoint":{"pointX":0.5,"pointY":0.5}},"layers":[{"animations":[],"initialState":{"affineTransform":[1,0,0,1,0,0],"masksToBounds":false,"rotation":0,"scale":1,"position":{"pointX":1474.616554054055,"pointY":413.9885979729729},"width":772,"sublayerTransform":[1,0,0,0,0,1,0,0,0,0,1,0,0,0,0,1],"contentsRect":{"y":0,"x":0,"width":1,"height":1},"opacity":1,"edgeAntialiasingMask":251658240,"height":301.9999999999999,"hidden":false,"anchorPoint":{"pointX":0.5,"pointY":0.5}},"objectID":"FE480AE0-80EB-4DDA-9725-1C2655EEFDB7","layers":[{"animations":[],"layers":[],"initialState":{"affineTransform":[1,0,0,1,0,0],"masksToBounds":false,"rotation":0,"scale":1,"position":{"pointX":385.8834459459449,"pointY":150.511402027027},"width":785,"sublayerTransform":[1,0,0,0,0,1,0,0,0,0,1,0,0,0,0,1],"contentsRect":{"y":0,"x":0,"width":1,"height":1},"opacity":1,"edgeAntialiasingMask":0,"height":547,"hidden":false,"anchorPoint":{"pointX":0.5,"pointY":0.5}},"texture":"FD5C3ED2E7434E6BDFE9C06C3ED1715E"}]}]}]}},{"effects":[{"beginTime":0,"baseLayer":{"animations":[],"initialState":{"affineTransform":[1,0,0,1,0,0],"masksToBounds":false,"rotation":0,"scale":1,"position":{"pointX":960,"pointY":540},"width":1920,"sublayerTransform":[1,0,0,0,0,1,0,0,0,0,1,0,0,0,0,1],"contentsRect":{"y":0,"x":0,"width":1,"height":1},"opacity":1,"edgeAntialiasingMask":251658240,"height":1080,"hidden":false,"anchorPoint":{"pointX":0.5,"pointY":0.5}},"objectID":"0","layers":[{"animations":[],"initialState":{"affineTransform":[1,0,0,1,0,0],"masksToBounds":false,"rotation":0,"scale":1,"position":{"pointX":960,"pointY":540},"width":1920,"sublayerTransform":[1,0,0,0,0,1,0,0,0,0,1,-0.0003500791246677598,0,0,0,1],"contentsRect":{"y":0,"x":0,"width":1,"height":1},"opacity":1,"edgeAntialiasingMask":251658240,"height":1080,"hidden":false,"anchorPoint":{"pointX":0.5,"pointY":0.5}},"layers":[{"animations":[],"layers":[],"initialState":{"affineTransform":[1,0,0,1,0,0],"masksToBounds":false,"rotation":0,"scale":1,"position":{"pointX":960,"pointY":540},"width":1920,"sublayerTransform":[1,0,0,0,0,1,0,0,0,0,1,0,0,0,0,1],"contentsRect":{"y":0,"x":0,"width":1,"height":1},"opacity":1,"edgeAntialiasingMask":0,"height":1080,"hidden":false,"anchorPoint":{"pointX":0.5,"pointY":0.5}},"texture":"B20313EA5DF59806F414B64E69A6A7E8"},{"animations":[{"timeOffset":0,"from":{"scalar":false},"beginTime":0,"repeatCount":0,"fillMode":"both","property":"hidden","autoreverses":false,"duration":0.01,"to":{"scalar":true}}],"layers":[],"initialState":{"affineTransform":[1,0,0,1,0,0],"masksToBounds":false,"rotation":0,"scale":1,"position":{"pointX":960,"pointY":540},"width":1920,"sublayerTransform":[1,0,0,0,0,1,0,0,0,0,1,0,0,0,0,1],"contentsRect":{"y":0,"x":0,"width":1,"height":1},"opacity":1,"edgeAntialiasingMask":0,"height":1080,"hidden":false,"anchorPoint":{"pointX":0.5,"pointY":0.5}},"texture":"16CEFB3D535DEAF8E33B75781567E5AB"}]}]},"effects":[],"duration":0.01,"type":"transition","name":"none","objectID":"0"}],"automaticPlay":false,"hyperlinks":[],"accessibility":[{"text":"Decorators","targetRectangle":{"y":98,"x":683.024,"width":553.9520000000001,"height":134}},{"text":"Skærmbillede 2016-09-28 kl. 11.42.25.png","targetRectangle":{"y":262.988597972973,"x":1088.616554054055,"width":772,"height":301.9999999999999}},{"text":"I feared these","targetRectangle":{"y":260,"x":182.4999984047963,"width":291.11264,"height":56}},{"text":"Turns out that they work quite well","targetRectangle":{"y":316,"x":182.4999984047963,"width":714.48468,"height":109.6900015473366}},{"text":"Prefixed with an @","targetRectangle":{"y":425.6900015473366,"x":182.4999984047963,"width":386.74636,"height":109.6900015473366}},{"text":"@Injectable() -> Service","targetRectangle":{"y":535.3800030946732,"x":232.4999984047963,"width":508.2168,"height":109.6900015473366}},{"text":"@Component() -> Component","targetRectangle":{"y":645.0700046420097,"x":232.4999984047963,"width":637.0691600000001,"height":109.6900015473366}},{"text":"@ngModule() -> Only used for app module in demo","targetRectangle":{"y":754.7600061893463,"x":232.4999984047963,"width":1091.95632,"height":109.6900015473366}},{"text":"Spot them in the coming slides and in the demo","targetRectangle":{"y":864.4500077366829,"x":182.4999984047963,"width":1009.85612,"height":109.6900015473366}}],"baseLayer":{"animations":[],"initialState":{"affineTransform":[1,0,0,1,0,0],"masksToBounds":false,"rotation":0,"scale":1,"position":{"pointX":960,"pointY":540},"width":1920,"sublayerTransform":[1,0,0,0,0,1,0,0,0,0,1,0,0,0,0,1],"contentsRect":{"y":0,"x":0,"width":1,"height":1},"opacity":1,"edgeAntialiasingMask":251658240,"height":1080,"hidden":false,"anchorPoint":{"pointX":0.5,"pointY":0.5}},"objectID":"0","layers":[{"animations":[],"initialState":{"affineTransform":[1,0,0,1,0,0],"masksToBounds":false,"rotation":0,"scale":1,"position":{"pointX":960,"pointY":540},"width":1920,"sublayerTransform":[1,0,0,0,0,1,0,0,0,0,1,-0.0003500791246677598,0,0,0,1],"contentsRect":{"y":0,"x":0,"width":1,"height":1},"opacity":1,"edgeAntialiasingMask":251658240,"height":1080,"hidden":false,"anchorPoint":{"pointX":0.5,"pointY":0.5}},"layers":[{"animations":[],"layers":[],"initialState":{"affineTransform":[1,0,0,1,0,0],"masksToBounds":false,"rotation":0,"scale":1,"position":{"pointX":960,"pointY":540},"width":1920,"sublayerTransform":[1,0,0,0,0,1,0,0,0,0,1,0,0,0,0,1],"contentsRect":{"y":0,"x":0,"width":1,"height":1},"opacity":1,"edgeAntialiasingMask":0,"height":1080,"hidden":false,"anchorPoint":{"pointX":0.5,"pointY":0.5}},"texture":"16CEFB3D535DEAF8E33B75781567E5AB"}]}]}}]}